camerakit/__init__.py
camerakit/calibration.py
camerakit/capture.py
camerakit/version.py
camerakit/core/__init__.py
camerakit/core/calibration_data.py
camerakit/core/calibration_file.py
camerakit/core/camera.py
camerakit/utils/__init__.py
camerakit/utils/calib.py
camerakit/utils/calibration.py
camerakit/utils/common.py
camerakit/utils/sync.py
camerakit/utils/pose/__init__.py
camerakit/utils/pose/from_board_outer.py
camerakit/utils/pose/from_keypoints.py
camerakit-1.0.0.dist-info/licenses/LICENSE
camerakit-1.0.0.dist-info/METADATA
camerakit-1.0.0.dist-info/WHEEL
camerakit-1.0.0.dist-info/entry_points.txt
camerakit-1.0.0.dist-info/top_level.txt
camerakit-1.0.0.dist-info/RECORD
