Metadata-Version: 2.4
Name: camerakit
Version: 1.0.0
Summary: CLI Tools and Python API for Camera Calibration and Synchronized Capture
Home-page: https://github.com/saifkhichi96/camerakit
Author: Saif Khan
Author-email: saifkhichi96@gmail.com
License: MIT License
Project-URL: Bug Tracker, https://github.com/saifkhichi96/camerakit/issues
Keywords: camera,calibration,synchronized capture
Platform: any
Classifier: Programming Language :: Python :: 3
Classifier: Development Status :: 4 - Beta
Classifier: Intended Audience :: Science/Research
Classifier: Intended Audience :: Developers
Classifier: Intended Audience :: Information Technology
Classifier: Intended Audience :: End Users/Desktop
Classifier: License :: OSI Approved :: MIT License
Classifier: Operating System :: OS Independent
Classifier: Topic :: Scientific/Engineering
Classifier: Topic :: Scientific/Engineering :: Image Processing
Classifier: Topic :: Multimedia :: Video
Classifier: Topic :: Multimedia :: Graphics
Classifier: Topic :: Software Development :: Libraries :: Python Modules
License-File: LICENSE
Requires-Dist: easydict
Requires-Dist: matplotlib
Requires-Dist: mpl_interactions
Requires-Dist: numpy
Requires-Dist: opencv-python
Requires-Dist: toml
Dynamic: license-file
